sonolus_fastapi/__init__.py
sonolus_fastapi/index.py
sonolus_fastapi/backend/__init__.py
sonolus_fastapi/backend/backend.py
sonolus_fastapi/backend/database.py
sonolus_fastapi/backend/factory.py
sonolus_fastapi/backend/json.py
sonolus_fastapi/backend/memory.py
sonolus_fastapi/model/ServerItemCommunityComment.py
sonolus_fastapi/model/ServerItemCommunityCommentList.py
sonolus_fastapi/model/ServerItemCommunityInfo.py
sonolus_fastapi/model/ServerItemDetails.py
sonolus_fastapi/model/ServerItemInfo.py
sonolus_fastapi/model/ServerItemLeaderboardDetails.py
sonolus_fastapi/model/ServerItemLeaderboardRecord.py
sonolus_fastapi/model/ServerItemList.py
sonolus_fastapi/model/ServerMessage.py
sonolus_fastapi/model/ServerOption.py
sonolus_fastapi/model/__init__.py
sonolus_fastapi/model/base.py
sonolus_fastapi/model/common.py
sonolus_fastapi/model/icon.py
sonolus_fastapi/model/pack.py
sonolus_fastapi/model/server_info.py
sonolus_fastapi/model/sonolus_types.py
sonolus_fastapi/model/text.py
sonolus_fastapi/model/userprofile.py
sonolus_fastapi/model/Request/ServerAuthenticateExternal.py
sonolus_fastapi/model/Request/ServerSubmitItemCommunityActionRequest.py
sonolus_fastapi/model/Request/ServerSubmitLevelResultRequest.py
sonolus_fastapi/model/Request/__init__.py
sonolus_fastapi/model/Request/authenticate.py
sonolus_fastapi/model/Response/ServerAuthenticateExternal.py
sonolus_fastapi/model/Response/ServerSubmitItemActionResponse.py
sonolus_fastapi/model/Response/ServerSubmitItemCommunityActionResponse.py
sonolus_fastapi/model/Response/ServerSubmitLevelResultResponse.py
sonolus_fastapi/model/Response/__init__.py
sonolus_fastapi/model/Response/authenticate.py
sonolus_fastapi/model/items/__init__.py
sonolus_fastapi/model/items/background.py
sonolus_fastapi/model/items/effect.py
sonolus_fastapi/model/items/engine.py
sonolus_fastapi/model/items/level.py
sonolus_fastapi/model/items/particle.py
sonolus_fastapi/model/items/playlist.py
sonolus_fastapi/model/items/post.py
sonolus_fastapi-0.2.3.dist-info/METADATA
sonolus_fastapi-0.2.3.dist-info/WHEEL
sonolus_fastapi-0.2.3.dist-info/licenses/LICENSE
sonolus_fastapi-0.2.3.dist-info/RECORD
